dinoaircontroller.py
dinoaircontroller-0.0.2.dist-info/METADATA
dinoaircontroller-0.0.2.dist-info/WHEEL
dinoaircontroller-0.0.2.dist-info/top_level.txt
dinoaircontroller-0.0.2.dist-info/RECORD
